{"root_group":{"groups":[{"checks":[{"name":"response code /  is 200","path":"::open_main::response code /  is 200","id":"d5a237335b7872a00c3de6f4f758479f","passes":57,"fails":2},{"name":"response code /api/config is 200","path":"::open_main::response code /api/config is 200","id":"3b7d0e9e50183375b723ef44b5512c93","passes":59,"fails":0},{"name":"response code /api/quotes is 200","path":"::open_main::response code /api/quotes is 200","id":"3506aba4e594f326ad34a4e82184fe0f","passes":59,"fails":0},{"name":"response code /api/tools is 200","path":"::open_main::response code /api/tools is 200","id":"38a91204f74c5884464c3d5719f16d54","passes":59,"fails":0}],"name":"open_main","path":"::open_main","id":"0db921d6b7e3d976c48d0d193cbf86af","groups":[]},{"id":"5af2ec90f9ffc3954616345d9a276291","groups":[],"checks":[{"path":"::click_pizza_please::response code /api/pizza is 200","id":"f922317ce8c9d6c11e6c4dc0870949b0","passes":59,"fails":0,"name":"response code /api/pizza is 200"}],"name":"click_pizza_please","path":"::click_pizza_please"},{"name":"teardown","path":"::teardown","id":"a8a9942382e8ffe2e56ef29e664b8229","groups":[{"groups":[{"name":"request_from_influx","path":"::teardown::get_response_groups::request_from_influx","id":"ceb1386f406a81f76d1f0abc12872ed6","groups":[],"checks":[{"fails":0,"name":"response code /query?db=${influxdb}&q=${select} is 200","path":"::teardown::get_response_groups::request_from_influx::response code /query?db=${influxdb}&q=${select} is 200","id":"4e1732704a42dd254402dbb8b7336ed2","passes":2}]}],"checks":[],"name":"get_response_groups","path":"::teardown::get_response_groups","id":"b14cc1e7a50ae3c93143f1639edffc50"}],"checks":[]}],"checks":[],"name":"","path":"","id":"d41d8cd98f00b204e9800998ecf8427e"},"options":{"summaryTrendStats":["avg","min","med","max","p(90)","p(95)"],"summaryTimeUnit":"","noColor":false},"state":{"isStdOutTTY":true,"isStdErrTTY":true,"testRunDurationMs":42881.622},"metrics":{"http_req_connecting":{"type":"trend","contains":"time","values":{"avg":5.51813468013468,"min":0,"med":0,"max":233.935,"p(90)":0,"p(95)":0}},"http_req_receiving":{"values":{"min":0.024,"med":0.105,"max":7.556,"p(90)":0.18960000000000002,"p(95)":0.22079999999999989,"avg":0.17281144781144783},"type":"trend","contains":"time"},"iterations":{"type":"counter","contains":"default","values":{"count":98,"rate":2.285361313991341}},"data_sent":{"type":"counter","contains":"data","values":{"count":96680,"rate":2254.578896292682}},"http_reqs":{"type":"counter","contains":"default","values":{"count":297,"rate":6.926043982198248}},"http_req_sending":{"type":"trend","contains":"time","values":{"max":3.129,"p(90)":0.33880000000000005,"p(95)":0.37739999999999996,"avg":0.216912457912458,"min":0.024,"med":0.184}},"vus_max":{"contains":"default","values":{"value":11,"min":11,"max":11},"type":"gauge"},"http_req_duration":{"contains":"time","values":{"avg":251.44827609427603,"min":5.137,"med":164.37,"max":10148.817,"p(90)":263.2622,"p(95)":294.17},"type":"trend"},"http_req_tls_handshaking":{"type":"trend","contains":"time","values":{"med":0,"max":216.767,"p(90)":0,"p(95)":0,"avg":5.522222222222222,"min":0}},"data_received":{"type":"counter","contains":"data","values":{"count":382599,"rate":8922.213809916053}},"iteration_duration":{"type":"trend","contains":"time","values":{"avg":798.6712741836734,"min":0.379084,"med":863.171146,"max":11118.7475,"p(90)":1178.8842544000001,"p(95)":1256.2652830999996}},"http_req_failed":{"thresholds":{"rate<0.1":{"ok":true}},"type":"rate","contains":"default","values":{"rate":0.006734006734006734,"passes":2,"fails":295}},"http_req_duration{expected_response:true}":{"values":{"min":5.137,"med":163.901,"max":377.505,"p(90)":261.3044,"p(95)":291.98879999999997,"avg":184.3661491525423},"type":"trend","contains":"time"},"http_req_blocked":{"type":"trend","contains":"time","values":{"med":0.001,"max":450.964,"p(90)":0.003,"p(95)":0.003,"avg":11.278484848484934,"min":0}},"http_req_waiting":{"type":"trend","contains":"time","values":{"med":164.025,"max":10148.539,"p(90)":263.0806,"p(95)":293.7562,"avg":251.05855218855208,"min":0.52}},"group_duration":{"type":"trend","contains":"time","values":{"p(95)":1011.7670982,"avg":640.7679043606556,"min":8.321959,"med":304.8477495,"max":10919.897875,"p(90)":919.3884542000001}},"vus":{"type":"gauge","contains":"default","values":{"value":1,"min":0,"max":4}},"checks":{"type":"rate","contains":"default","values":{"rate":0.9932659932659933,"passes":295,"fails":2}}},"setup_data":{"test_id":17}}